setup.py
gausbinom_probability/Binomialdistribution.py
gausbinom_probability/Gaussiandistribution.py
gausbinom_probability/Generaldistribution.py
gausbinom_probability/__init__.py
gausbinom_probability.egg-info/PKG-INFO
gausbinom_probability.egg-info/SOURCES.txt
gausbinom_probability.egg-info/dependency_links.txt
gausbinom_probability.egg-info/not-zip-safe
gausbinom_probability.egg-info/top_level.txt