Metadata-Version: 1.0
Name: gausbinom-probability
Version: 1.0
Summary: Gaussian and Binomial distributions
Home-page: UNKNOWN
Author: Ishan Pathirana
Author-email: myemail@gmail.com
License: UNKNOWN
Platform: UNKNOWN
